{
   "nextLineId":"6",
   "nextStationId":"97",
   "systemId":"1",
   "map":{
      "lines":{
         "0":{
            "id":"0",
            "color":"#4363d8",
            "name":"Blue Line",
            "stationIds":[
               "2",
               "1",
               "0",
               "95",
               "94",
               "2",
               "3",
               "4",
               "5",
               "6",
               "7",
               "8",
               "33",
               "86",
               "87",
               "88",
               "89",
               "90",
               "91",
               "92",
               "93",
               "83",
               "85"
            ]
         },
         "1":{
            "id":"1",
            "color":"#e6194b",
            "name":"Red Line",
            "stationIds":[
               "55",
               "10",
               "11",
               "85",
               "13",
               "14",
               "15",
               "16",
               "17",
               "18",
               "19",
               "20",
               "21",
               "22"
            ]
         },
         "2":{
            "id":"2",
            "color":"#3cb44b",
            "name":"Green Line",
            "stationIds":[
               "23",
               "24",
               "25",
               "26",
               "27",
               "28",
               "29",
               "30",
               "31",
               "32",
               "33",
               "34",
               "35",
               "36"
            ]
         },
         "3":{
            "id":"3",
            "color":"#ffe119",
            "name":"Gold Line",
            "stationIds":[
               "37",
               "38",
               "39",
               "40",
               "41",
               "42",
               "43",
               "44",
               "45",
               "46",
               "47",
               "48",
               "49",
               "50",
               "51",
               "52",
               "53",
               "54",
               "55",
               "56",
               "57",
               "58",
               "59",
               "60",
               "61",
               "62",
               "63"
            ]
         },
         "4":{
            "id":"4",
            "color":"#911eb4",
            "name":"Purple Line",
            "stationIds":[
               "64",
               "65",
               "14",
               "13",
               "85",
               "11",
               "10",
               "55"
            ]
         },
         "5":{
            "id":"5",
            "color":"#42d4f4",
            "name":"Expo Line",
            "stationIds":[
               "66",
               "67",
               "68",
               "69",
               "70",
               "71",
               "72",
               "73",
               "74",
               "75",
               "76",
               "77",
               "78",
               "79",
               "80",
               "81",
               "82",
               "83",
               "85"
            ]
         }
      },
      "stations":{
         "0":{
            "id":"0",
            "lat":33.7680699,
            "lng":-118.19292,
            "name":"Downtown Long Beach Station",
            "info":{
               "numNearbyBuildings":167,
               "buildingArea":330818.2035226985,
               "areaByUsage":{
                  "residential":28676.207524014662,
                  "hotel":21057.321278543113,
                  "commercial":117950.14017619097,
                  "industrial":0,
                  "civic":5949.5968357232505,
                  "other/unknown":157184.9377082265,
                  "park":5848.492074073968
               },
               "densityScore":165
            }
         },
         "1":{
            "id":"1",
            "lat":33.7722599,
            "lng":-118.1937,
            "name":"Pacific Ave Station",
            "info":{
               "numNearbyBuildings":407,
               "buildingArea":268403.145119424,
               "areaByUsage":{
                  "residential":77503.58149753635,
                  "hotel":304.8243542528846,
                  "commercial":83697.73549250604,
                  "industrial":0,
                  "civic":0,
                  "other/unknown":106897.00377512873,
                  "park":1553.1717309885491
               },
               "densityScore":145
            }
         },
         "2":{
            "id":"2",
            "lat":33.7818299,
            "lng":-118.18938,
            "name":"Anaheim Street Station",
            "info":{
               "numNearbyBuildings":596,
               "buildingArea":200600.9053122675,
               "areaByUsage":{
                  "residential":74648.34114192172,
                  "hotel":2462.3619660037493,
                  "commercial":66441.37436467015,
                  "industrial":903.3389936604477,
                  "civic":15172.86176855449,
                  "other/unknown":40972.62707745686,
                  "park":10013.170314608025
               },
               "densityScore":128
            }
         },
         "3":{
            "id":"3",
            "lat":33.7890899,
            "lng":-118.18938,
            "name":"Pacific Coast Hwy Station"
         },
         "4":{
            "id":"4",
            "lat":33.8070799,
            "lng":-118.18983,
            "name":"Willow Street Station"
         },
         "5":{
            "id":"5",
            "lat":33.8198599,
            "lng":-118.19609,
            "name":"Wardlow Station"
         },
         "6":{
            "id":"6",
            "lat":33.8482199,
            "lng":-118.21102,
            "name":"Del Amo Station"
         },
         "7":{
            "id":"7",
            "lat":33.8760799,
            "lng":-118.2225,
            "name":"Artesia Station"
         },
         "8":{
            "id":"8",
            "lat":33.8974899,
            "lng":-118.22425,
            "name":"Compton Station",
            "info":{
               "numNearbyBuildings":691,
               "buildingArea":160697.88944198564,
               "areaByUsage":{
                  "residential":55713.18440534848,
                  "hotel":0,
                  "commercial":42517.99585110147,
                  "industrial":2288.697521533943,
                  "civic":0,
                  "other/unknown":60178.011664001424,
                  "park":1470.101127338088
               },
               "densityScore":110
            }
         },
         "10":{
            "id":"10",
            "lat":34.0548999,
            "lng":-118.24606,
            "name":"Civic Center / Grand Park Station"
         },
         "11":{
            "id":"11",
            "lat":34.0493199,
            "lng":-118.25126,
            "name":"Pershing Square Station",
            "info":{
               "numNearbyBuildings":265,
               "buildingArea":413404.5272155139,
               "areaByUsage":{
                  "residential":51995.51342477854,
                  "hotel":33294.41687228642,
                  "commercial":163346.5628530875,
                  "industrial":2897.0146965639033,
                  "civic":0,
                  "other/unknown":161871.01936879754,
                  "park":40499.992510855045
               },
               "densityScore":225
            }
         },
         "13":{
            "id":"13",
            "lat":34.0563699,
            "lng":-118.27488,
            "name":"Westlake / Macarthur Park Station"
         },
         "14":{
            "id":"14",
            "lat":34.0626999,
            "lng":-118.29008,
            "name":"Wilshire / Vermont Station",
            "info":{
               "numNearbyBuildings":301,
               "buildingArea":294944.2234311341,
               "areaByUsage":{
                  "residential":100001.40024163913,
                  "hotel":7439.288981372222,
                  "commercial":104532.29637335445,
                  "industrial":2004.7131684472918,
                  "civic":1617.7848689444022,
                  "other/unknown":79348.73979737666,
                  "park":0
               },
               "densityScore":152
            }
         },
         "15":{
            "id":"15",
            "lat":34.0765299,
            "lng":-118.29169,
            "name":"Vermont / Beverly Station"
         },
         "16":{
            "id":"16",
            "lat":34.0899099,
            "lng":-118.29173,
            "name":"Vermont / Santa Monica Station"
         },
         "17":{
            "id":"17",
            "lat":34.0977099,
            "lng":-118.29176,
            "name":"Vermont / Sunset Station"
         },
         "18":{
            "id":"18",
            "lat":34.1017399,
            "lng":-118.30812,
            "name":"Hollywood / Western Station"
         },
         "19":{
            "id":"19",
            "lat":34.1016299,
            "lng":-118.32518,
            "name":"Hollywood / Vine Station"
         },
         "20":{
            "id":"20",
            "lat":34.1015499,
            "lng":-118.33855,
            "name":"Hollywood / Highland Station"
         },
         "21":{
            "id":"21",
            "lat":34.1399999,
            "lng":-118.3627,
            "name":"Universal / Studio City Station"
         },
         "22":{
            "id":"22",
            "lat":34.1684999,
            "lng":-118.37681,
            "name":"North Hollywood Station"
         },
         "23":{
            "id":"23",
            "lat":33.8946399,
            "lng":-118.3692,
            "name":"Redondo Beach Station"
         },
         "24":{
            "id":"24",
            "lat":33.9052999,
            "lng":-118.38311,
            "name":"Douglas Station"
         },
         "25":{
            "id":"25",
            "lat":33.9160599,
            "lng":-118.38654,
            "name":"El Segundo Station"
         },
         "26":{
            "id":"26",
            "lat":33.9231999,
            "lng":-118.38757,
            "name":"Mariposa Station"
         },
         "27":{
            "id":"27",
            "lat":33.9296199,
            "lng":-118.37713,
            "name":"Aviation / Lax Station"
         },
         "28":{
            "id":"28",
            "lat":33.9334099,
            "lng":-118.3516,
            "name":"Hawthorne / Lennox Station"
         },
         "29":{
            "id":"29",
            "lat":33.9251999,
            "lng":-118.32655,
            "name":"Crenshaw Station"
         },
         "30":{
            "id":"30",
            "lat":33.9286799,
            "lng":-118.29173,
            "name":"Vermont / Athens Station"
         },
         "31":{
            "id":"31",
            "lat":33.9287099,
            "lng":-118.2811,
            "name":"Harbor Freeway Station"
         },
         "32":{
            "id":"32",
            "lat":33.9274599,
            "lng":-118.26522,
            "name":"Avalon Station"
         },
         "33":{
            "id":"33",
            "lat":33.9282599,
            "lng":-118.23805,
            "name":"Willowbrook - Rosa Parks Station",
            "info":{
               "numNearbyBuildings":638,
               "buildingArea":113561.62978098243,
               "areaByUsage":{
                  "residential":46434.380490400385,
                  "hotel":433.8601960095044,
                  "commercial":18694.920132735668,
                  "industrial":0,
                  "civic":959.3969380883887,
                  "other/unknown":47039.07202374838,
                  "park":4656.432246242653
               },
               "densityScore":87
            }
         },
         "34":{
            "id":"34",
            "lat":33.9248799,
            "lng":-118.20994,
            "name":"Long Beach Blvd Station"
         },
         "35":{
            "id":"35",
            "lat":33.9130699,
            "lng":-118.1406,
            "name":"Lakewood Blvd Station"
         },
         "36":{
            "id":"36",
            "lat":33.9140299,
            "lng":-118.10472,
            "name":"Norwalk Station"
         },
         "37":{
            "id":"37",
            "lat":34.1368099,
            "lng":-117.89164,
            "name":"Apu / Citrus College Station"
         },
         "38":{
            "id":"38",
            "lat":34.1358599,
            "lng":-117.90663,
            "name":"Azusa Downtown Station"
         },
         "39":{
            "id":"39",
            "lat":34.1290499,
            "lng":-117.93251,
            "name":"Irwindale Station"
         },
         "40":{
            "id":"40",
            "lat":34.1325199,
            "lng":-117.96768,
            "name":"Duarte / City Of Hope Station"
         },
         "41":{
            "id":"41",
            "lat":34.1331599,
            "lng":-118.00347,
            "name":"Monrovia Station"
         },
         "42":{
            "id":"42",
            "lat":34.1428599,
            "lng":-118.0292,
            "name":"Arcadia Station"
         },
         "43":{
            "id":"43",
            "lat":34.1477499,
            "lng":-118.08121,
            "name":"Sierra Madre Villa Station"
         },
         "44":{
            "id":"44",
            "lat":34.1524199,
            "lng":-118.11435,
            "name":"Allen Station"
         },
         "45":{
            "id":"45",
            "lat":34.1518099,
            "lng":-118.13139,
            "name":"Lake Station"
         },
         "46":{
            "id":"46",
            "lat":34.1483599,
            "lng":-118.14751,
            "name":"Memorial Park Station"
         },
         "47":{
            "id":"47",
            "lat":34.1419099,
            "lng":-118.14821,
            "name":"Del Mar Station"
         },
         "48":{
            "id":"48",
            "lat":34.1335199,
            "lng":-118.14813,
            "name":"Fillmore Station"
         },
         "49":{
            "id":"49",
            "lat":34.1151899,
            "lng":-118.15789,
            "name":"South Pasadena Station"
         },
         "50":{
            "id":"50",
            "lat":34.1111799,
            "lng":-118.19261,
            "name":"Highland Park Station"
         },
         "51":{
            "id":"51",
            "lat":34.0982399,
            "lng":-118.20671,
            "name":"Southwest Museum Station"
         },
         "52":{
            "id":"52",
            "lat":34.0872299,
            "lng":-118.21321,
            "name":"Heritage Square / Arroyo Station"
         },
         "53":{
            "id":"53",
            "lat":34.0809499,
            "lng":-118.22043,
            "name":"Lincoln Heights / Cypress Park Station"
         },
         "54":{
            "id":"54",
            "lat":34.0638599,
            "lng":-118.23584,
            "name":"Chinatown Station"
         },
         "55":{
            "id":"55",
            "lat":34.0560599,
            "lng":-118.23476,
            "name":"Union Station",
            "info":{
               "numNearbyBuildings":146,
               "buildingArea":257783.84584846144,
               "areaByUsage":{
                  "residential":5073.136661070922,
                  "hotel":2169.1582534878235,
                  "commercial":32910.56188011478,
                  "industrial":19085.76415572574,
                  "civic":18433.596610382883,
                  "other/unknown":180111.62828767934,
                  "park":8350.253686113007
               },
               "weightedLevel":5,
               "densityScore":250
            }
         },
         "56":{
            "id":"56",
            "lat":34.0500999,
            "lng":-118.2379,
            "name":"Little Tokyo / Arts District Station"
         },
         "57":{
            "id":"57",
            "lat":34.0476299,
            "lng":-118.22594,
            "name":"Pico / Aliso Station"
         },
         "58":{
            "id":"58",
            "lat":34.0472199,
            "lng":-118.21965,
            "name":"Mariachi Plaza / Boyle Heights Station"
         },
         "59":{
            "id":"59",
            "lat":34.0437499,
            "lng":-118.21006,
            "name":"Soto Station"
         },
         "60":{
            "id":"60",
            "lat":34.0342999,
            "lng":-118.19218,
            "name":"Indiana Station"
         },
         "61":{
            "id":"61",
            "lat":34.0333199,
            "lng":-118.16814,
            "name":"Maravilla Station"
         },
         "62":{
            "id":"62",
            "lat":34.0333599,
            "lng":-118.16121,
            "name":"East La Civic Center Station"
         },
         "63":{
            "id":"63",
            "lat":34.0333999,
            "lng":-118.15447,
            "name":"Atlantic Station"
         },
         "64":{
            "id":"64",
            "lat":34.0616899,
            "lng":-118.30876,
            "name":"Wilshire / Western Station"
         },
         "65":{
            "id":"65",
            "lat":34.0617499,
            "lng":-118.30146,
            "name":"Wilshire / Normandie Station"
         },
         "66":{
            "id":"66",
            "lat":34.0140099,
            "lng":-118.49138,
            "name":"Downtown Santa Monica Station"
         },
         "67":{
            "id":"67",
            "lat":34.0231599,
            "lng":-118.48037,
            "name":"17th Street / Smc Station"
         },
         "68":{
            "id":"68",
            "lat":34.0279899,
            "lng":-118.46912,
            "name":"26th Street / Bergamot Station"
         },
         "69":{
            "id":"69",
            "lat":34.0317099,
            "lng":-118.4529,
            "name":"Expo / Bundy Station"
         },
         "70":{
            "id":"70",
            "lat":34.0354099,
            "lng":-118.43423,
            "name":"Expo / Sepulveda Station"
         },
         "71":{
            "id":"71",
            "lat":34.0368199,
            "lng":-118.42458,
            "name":"Westwood / Rancho Park Station"
         },
         "72":{
            "id":"72",
            "lat":34.0293199,
            "lng":-118.40425,
            "name":"Palms Station"
         },
         "73":{
            "id":"73",
            "lat":34.0278999,
            "lng":-118.38899,
            "name":"Culver City Station"
         },
         "74":{
            "id":"74",
            "lat":34.0263599,
            "lng":-118.37212,
            "name":"La Cienega / Jefferson Station"
         },
         "75":{
            "id":"75",
            "lat":34.0247999,
            "lng":-118.35516,
            "name":"Expo / La Brea / Ethel Bradley Station"
         },
         "76":{
            "id":"76",
            "lat":34.0239799,
            "lng":-118.34609,
            "name":"Farmdale Station"
         },
         "77":{
            "id":"77",
            "lat":34.0225299,
            "lng":-118.33508,
            "name":"Expo / Crenshaw Station"
         },
         "78":{
            "id":"78",
            "lat":34.0183299,
            "lng":-118.30891,
            "name":"Expo / Western Station"
         },
         "79":{
            "id":"79",
            "lat":34.0182399,
            "lng":-118.29154,
            "name":"Expo / Vermont Station",
            "info":{
               "numNearbyBuildings":612,
               "buildingArea":239194.05430646983,
               "areaByUsage":{
                  "residential":74692.46855314974,
                  "hotel":0,
                  "commercial":2699.711108749955,
                  "industrial":0,
                  "civic":52187.917244845994,
                  "other/unknown":109613.95739972407,
                  "park":164803.6478140544
               },
               "densityScore":191
            }
         },
         "80":{
            "id":"80",
            "lat":34.0182299,
            "lng":-118.28573,
            "name":"Expo Park / Usc Station"
         },
         "81":{
            "id":"81",
            "lat":34.0221199,
            "lng":-118.27812,
            "name":"Jefferson / Usc Station",
            "info":{
               "numNearbyBuildings":246,
               "buildingArea":262886.64793365967,
               "areaByUsage":{
                  "residential":28475.512271674586,
                  "hotel":6101.429159658906,
                  "commercial":57167.257497685954,
                  "industrial":61682.91269372305,
                  "civic":33257.93508578566,
                  "other/unknown":76201.60122513126,
                  "park":19.18937207728143
               },
               "densityScore":134
            }
         },
         "82":{
            "id":"82",
            "lat":34.0291099,
            "lng":-118.2736,
            "name":"Lattc / Ortho Institute Station"
         },
         "83":{
            "id":"83",
            "lat":34.0407299,
            "lng":-118.26612,
            "name":"Pico Station",
            "info":{
               "numNearbyBuildings":186,
               "buildingArea":509108.53195785865,
               "areaByUsage":{
                  "residential":61659.32576292948,
                  "hotel":2678.3806855785087,
                  "commercial":82287.74487457091,
                  "industrial":38201.3889627475,
                  "civic":30783.286588658568,
                  "other/unknown":293498.40508337406,
                  "park":7199.383540267742
               },
               "densityScore":249
            }
         },
         "84":{
            "id":"84",
            "lat":34.0486099,
            "lng":-118.25882,
            "name":"7th Street / Metro Center Station - Metro Blue & Expo Lines",
            "info":{
               "numNearbyBuildings":197,
               "buildingArea":424493.8259177422,
               "areaByUsage":{
                  "residential":76821.46224479028,
                  "hotel":19710.640357476364,
                  "commercial":156484.55945700724,
                  "industrial":872.4745947802134,
                  "civic":0,
                  "other/unknown":170604.6892636882,
                  "park":4401.162152855617
               },
               "weightedLevel":20,
               "densityScore":1389
            }
         },
         "85":{
            "lng":-118.25881125729447,
            "lat":34.04868406000135,
            "id":"85",
            "name":"7th Street / Metro Center",
            "info":{
               "numNearbyBuildings":195,
               "buildingArea":421386.8126115247,
               "areaByUsage":{
                  "residential":74812.7900771428,
                  "hotel":19710.640357476364,
                  "commercial":155386.2183184372,
                  "industrial":872.4745947802134,
                  "civic":0,
                  "other/unknown":170604.6892636882,
                  "park":4401.162152855617
               },
               "weightedLevel":20,
               "densityScore":1379
            }
         },
         "86":{
            "lng":-118.24317555969961,
            "lat":33.94258111374465,
            "id":"86",
            "name":"103rd Street / Watts Towers Station",
            "info":{
               "numNearbyBuildings":681,
               "buildingArea":146594.6467686879,
               "areaByUsage":{
                  "residential":64209.254416590156,
                  "hotel":0,
                  "commercial":18951.836820469267,
                  "industrial":129.588446919263,
                  "civic":1461.4737441470543,
                  "other/unknown":61842.493340562214,
                  "park":15021.130893875728
               },
               "densityScore":109
            }
         },
         "87":{
            "lng":-118.2432662590148,
            "lat":33.959741921383994,
            "id":"87",
            "name":"Firestone Station",
            "info":{
               "numNearbyBuildings":1303,
               "buildingArea":177031.69781993038,
               "areaByUsage":{
                  "residential":85695.81715198158,
                  "hotel":360.09145360091816,
                  "commercial":17147.375680381876,
                  "industrial":6755.643043657494,
                  "civic":4455.575116848369,
                  "other/unknown":62617.195373460134,
                  "park":27507.347517458744
               },
               "densityScore":161
            }
         },
         "88":{
            "lng":-118.24328973952889,
            "lat":33.9741085599733,
            "id":"88",
            "name":"Florence Station",
            "info":{
               "numNearbyBuildings":1240,
               "buildingArea":188396.45517444043,
               "areaByUsage":{
                  "residential":82270.60935461447,
                  "hotel":0,
                  "commercial":28380.632438245026,
                  "industrial":11568.469166633839,
                  "civic":0,
                  "other/unknown":66176.74421494726,
                  "park":40523.30028749847
               },
               "densityScore":170
            }
         },
         "89":{
            "lng":-118.24332342518237,
            "lat":33.98899675953419,
            "id":"89",
            "name":"Slauson Station",
            "info":{
               "numNearbyBuildings":814,
               "buildingArea":172760.2973358939,
               "areaByUsage":{
                  "residential":45063.821833594164,
                  "hotel":0,
                  "commercial":10602.038995333261,
                  "industrial":75600.90447056123,
                  "civic":456.499368801691,
                  "other/unknown":41037.03266760357,
                  "park":34184.05437852865
               },
               "densityScore":138
            }
         },
         "90":{
            "lng":-118.24330237654334,
            "lat":34.003258247983496,
            "id":"90",
            "name":"Vernon Station",
            "info":{
               "numNearbyBuildings":1113,
               "buildingArea":225117.56961128043,
               "areaByUsage":{
                  "residential":56495.845217601134,
                  "hotel":0,
                  "commercial":17367.925644193805,
                  "industrial":96443.16922851626,
                  "civic":0,
                  "other/unknown":54810.6295209693,
                  "park":10888.03683589415
               },
               "densityScore":165
            }
         },
         "91":{
            "lng":-118.2430757273684,
            "lat":34.01991089896612,
            "id":"91",
            "name":"Washington Station",
            "info":{
               "numNearbyBuildings":442,
               "buildingArea":268078.48137155594,
               "areaByUsage":{
                  "residential":13949.825126834168,
                  "hotel":0,
                  "commercial":27978.649985998567,
                  "industrial":206540.72192094263,
                  "civic":0,
                  "other/unknown":19609.284337780482,
                  "park":0
               },
               "densityScore":146
            }
         },
         "92":{
            "lng":-118.25585760199579,
            "lat":34.02696884297097,
            "id":"92",
            "name":"San Pedro St Station",
            "info":{
               "numNearbyBuildings":730,
               "buildingArea":245253.14024335085,
               "areaByUsage":{
                  "residential":37321.82851410533,
                  "hotel":0,
                  "commercial":34304.24531591521,
                  "industrial":124380.03172398321,
                  "civic":1695.475116173163,
                  "other/unknown":47551.55957317386,
                  "park":0
               },
               "densityScore":150
            }
         },
         "93":{
            "lng":-118.26893871097502,
            "lat":34.03297029489485,
            "id":"93",
            "name":"Grand / LATTC Station",
            "info":{
               "numNearbyBuildings":183,
               "buildingArea":239616.5729253106,
               "areaByUsage":{
                  "residential":33465.05265878173,
                  "hotel":384.1088358389866,
                  "commercial":48736.13464895722,
                  "industrial":45239.63915466929,
                  "civic":11750.004042047705,
                  "other/unknown":100041.63358501576,
                  "park":0
               },
               "densityScore":120
            }
         },
         "94":{
            "lng":-118.1893938213804,
            "lat":33.77358526614992,
            "id":"94",
            "name":"5th Street Station",
            "info":{
               "numNearbyBuildings":412,
               "buildingArea":259798.94475021985,
               "areaByUsage":{
                  "residential":71974.89918157394,
                  "hotel":1576.2108590585008,
                  "commercial":95246.43047295415,
                  "industrial":0,
                  "civic":1373.049882850501,
                  "other/unknown":89628.35435378259,
                  "park":1539.1715842068604
               },
               "densityScore":142
            }
         },
         "95":{
            "lng":-118.18941598261473,
            "lat":33.768723156941846,
            "id":"95",
            "name":"1st Street Station",
            "info":{
               "numNearbyBuildings":225,
               "buildingArea":316922.1831562611,
               "areaByUsage":{
                  "residential":20743.541537030287,
                  "hotel":31135.378959271613,
                  "commercial":154922.66875717437,
                  "industrial":0,
                  "civic":0,
                  "other/unknown":110120.5939027847,
                  "park":12273.760862925183
               },
               "densityScore":164
            }
         }
      },
      "title":"Los Angeles Metro"
   }
}
